{
  "$schema": "../Packages/Beckhoff.TwinCAT.HMI.Framework.12.748.0/runtimes/native1.12-tchmi/Schema/TchmiConfig.Schema.json",
  "basePath": "./framework",
  "scaleMode": "None",
  "startupView": "Desktop.view",
  "loginPage": "",
  "tcHmiServer": {
    "websocketIntervalTime": 500,
    "websocketTimeout": 10000,
    "websocketSystemTimeout": 0,
    "websocketSubscriptionMode": "Change"
  },
  "activeTheme": "Base",
  "themes": {
    "Base": {
      "resources": [
        {
          "name": "Themes/Base/Base.theme",
          "description": "",
          "type": "ThemedValues"
        },
        {
          "name": "Themes/Base/Style.css",
          "description": "",
          "type": "Stylesheet"
        },
        {
          "name": "Themes/Base/BaseStyle.css",
          "description": "Theme Stylesheet",
          "type": "Stylesheet"
        }
      ],
      "replacesThemeForControls": []
    }
  },
  "dependencyFiles": [
    {
      "name": "Fonts/Fonts.css",
      "description": "",
      "type": "Stylesheet"
    }
  ],
  "userControls": [],
  "content": [
    {
      "url": "Contents/Alarms.content",
      "preload": false,
      "keepAlive": false
    },
    {
      "url": "Contents/Diagnostics.content",
      "preload": false,
      "keepAlive": false
    },
    {
      "url": "Contents/Main.content",
      "preload": false,
      "keepAlive": false
    },
    {
      "url": "Contents/MetricUnits.content",
      "preload": false,
      "keepAlive": false
    },
    {
      "url": "Contents/Offsets.content",
      "preload": false,
      "keepAlive": false
    },
    {
      "url": "Contents/StandardUnits.content",
      "preload": false,
      "keepAlive": false
    },
    {
      "url": "Contents/Status.content",
      "preload": false,
      "keepAlive": false
    }
  ],
  "views": [
    {
      "url": "Desktop.view",
      "preload": false,
      "keepAlive": false
    }
  ],
  "userFunctions": [],
  "symbols": {
    "internal": {
      "Units": {
        "value": "Metric",
        "type": "tchmi:general#/definitions/STRING(80)",
        "persist": false,
        "readonly": false
      },
      "Unit": {
        "value": 1,
        "type": "tchmi:general#/definitions/INT",
        "persist": false,
        "readonly": false
      }
    }
  },
  "trigger": [],
  "actionTemplates": [],
  "languages": {
    "de-DE": "Localization\\de-DE.localization",
    "en-US": "Localization\\en-US.localization"
  },
  "languageFallback": "",
  "disableLoadingOptimization": false,
  "creatorSettings": {
    "viewport": {
      "defaultWidth": 1024,
      "defaultHeight": 768
    }
  },
  "binding": {
    "symbolError": "Ignore"
  },
  "packages": [
    {
      "name": "Beckhoff.TwinCAT.HMI.Controls",
      "basePath": "/Beckhoff.TwinCAT.HMI.Controls"
    },
    {
      "name": "Beckhoff.TwinCAT.HMI.Framework",
      "basePath": "/framework"
    },
    {
      "name": "Beckhoff.TwinCAT.HMI.Functions",
      "basePath": "/Beckhoff.TwinCAT.HMI.Functions"
    }
  ]
}